ankivalenz/__init__.py
ankivalenz/__main__.py
ankivalenz/anki_models.py
ankivalenz/generator.py
ankivalenz/html_parser.py
ankivalenz/main.py
ankivalenz/markdown_parser.py
ankivalenz/node_parser.py
ankivalenz/types.py
ankivalenz-1.0.2.dist-info/LICENSE
ankivalenz-1.0.2.dist-info/METADATA
ankivalenz-1.0.2.dist-info/WHEEL
ankivalenz-1.0.2.dist-info/entry_points.txt
ankivalenz-1.0.2.dist-info/RECORD
