Metadata-Version: 2.1
Name: ankivalenz
Version: 1.0.2
Summary: 
Author: Harry Vangberg
Author-email: harry@vangberg.name
Requires-Python: >=3.10,<4.0
Classifier: Programming Language :: Python :: 3
Classifier: Programming Language :: Python :: 3.10
Classifier: Programming Language :: Python :: 3.11
Classifier: Programming Language :: Python :: 3.12
Requires-Dist: bs4 (>=0.0.1,<0.0.3)
Requires-Dist: genanki (>=0.13.0,<0.14.0)
Requires-Dist: markdown-it-py (>=3.0.0,<4.0.0)
Requires-Dist: mdit-py-plugins (>=0.4.2,<0.5.0)
Requires-Dist: mistune (>=3.0.2,<4.0.0)
Requires-Dist: pyyaml (>=6.0.1)
Requires-Dist: typer (>=0.6.1,<0.16.0)
